[
    {
        "beetbox_id": "beetbox017",
        "coordinates": "POINT(44.286042 -117.224889)",
        "piler_id": "3",
        "temperature_time": "2024-10-08T08:08:32.000000",
        "temperature": 42.46
    },
    {
        "beetbox_id": "beetbox020",
        "coordinates": "POINT(44.298183 -117.230745)",
        "piler_id": "1",
        "temperature_time": "2024-10-12T17:29:28.000000",
        "temperature": 43.97
    },
    {
        "beetbox_id": "beetbox002",
        "coordinates": "POINT(44.29529 -117.230073)",
        "piler_id": "1",
        "temperature_time": "2024-10-08T06:12:40.000000",
        "temperature": 45.18
    },
    {
        "beetbox_id": "beetbox008",
        "coordinates": "POINT(44.288065 -117.228219)",
        "piler_id": "3",
        "temperature_time": "2024-10-09T11:25:13.000000",
        "temperature": 44.76
    },
    {
        "beetbox_id": "beetbox002",
        "coordinates": "POINT(44.293165 -117.231447)",
        "piler_id": "1",
        "temperature_time": "2024-10-10T01:22:28.000000",
        "temperature": 39.16
    },
    {
        "beetbox_id": "beetbox002",
        "coordinates": "POINT(44.299795 -117.233094)",
        "piler_id": "1",
        "temperature_time": "2024-10-12T15:46:42.000000",
        "temperature": 45.7
    },
    {
        "beetbox_id": "beetbox019",
        "coordinates": "POINT(44.301502 -117.22564)",
        "piler_id": "2",
        "temperature_time": "2024-10-08T18:05:37.000000",
        "temperature": 38.88
    },
    {
        "beetbox_id": "beetbox006",
        "coordinates": "POINT(44.282841 -117.230974)",
        "piler_id": "1",
        "temperature_time": "2024-10-12T02:16:30.000000",
        "temperature": 40.49
    },
    {
        "beetbox_id": "beetbox002",
        "coordinates": "POINT(44.299154 -117.21733)",
        "piler_id": "3",
        "temperature_time": "2024-10-08T05:42:57.000000",
        "temperature": 43.63
    },
    {
        "beetbox_id": "beetbox004",
        "coordinates": "POINT(44.285949 -117.223216)",
        "piler_id": "1",
        "temperature_time": "2024-10-08T02:40:31.000000",
        "temperature": 45.11
    },
    {
        "beetbox_id": "beetbox009",
        "coordinates": "POINT(44.288388 -117.215385)",
        "piler_id": "1",
        "temperature_time": "2024-10-12T06:08:23.000000",
        "temperature": 45.73
    },
    {
        "beetbox_id": "beetbox018",
        "coordinates": "POINT(44.286279 -117.219845)",
        "piler_id": "2",
        "temperature_time": "2024-10-09T10:50:13.000000",
        "temperature": 35.34
    },
    {
        "beetbox_id": "beetbox012",
        "coordinates": "POINT(44.293674 -117.217297)",
        "piler_id": "2",
        "temperature_time": "2024-10-12T03:48:14.000000",
        "temperature": 36.83
    },
    {
        "beetbox_id": "beetbox020",
        "coordinates": "POINT(44.283934 -117.225032)",
        "piler_id": "1",
        "temperature_time": "2024-10-08T00:23:16.000000",
        "temperature": 38.61
    },
    {
        "beetbox_id": "beetbox013",
        "coordinates": "POINT(44.287785 -117.217918)",
        "piler_id": "1",
        "temperature_time": "2024-10-11T20:43:19.000000",
        "temperature": 36.8
    },
    {
        "beetbox_id": "beetbox018",
        "coordinates": "POINT(44.293292 -117.217879)",
        "piler_id": "1",
        "temperature_time": "2024-10-10T09:22:44.000000",
        "temperature": 41.17
    },
    {
        "beetbox_id": "beetbox005",
        "coordinates": "POINT(44.285448 -117.232069)",
        "piler_id": "2",
        "temperature_time": "2024-10-09T04:05:11.000000",
        "temperature": 37.74
    },
    {
        "beetbox_id": "beetbox011",
        "coordinates": "POINT(44.286133 -117.231943)",
        "piler_id": "3",
        "temperature_time": "2024-10-08T02:30:13.000000",
        "temperature": 37.16
    },
    {
        "beetbox_id": "beetbox009",
        "coordinates": "POINT(44.282533 -117.218637)",
        "piler_id": "2",
        "temperature_time": "2024-10-08T00:54:41.000000",
        "temperature": 40.96
    },
    {
        "beetbox_id": "beetbox011",
        "coordinates": "POINT(44.285494 -117.217238)",
        "piler_id": "1",
        "temperature_time": "2024-10-08T08:13:50.000000",
        "temperature": 43.27
    },
    {
        "beetbox_id": "beetbox018",
        "coordinates": "POINT(44.290969 -117.230808)",
        "piler_id": "3",
        "temperature_time": "2024-10-09T21:44:16.000000",
        "temperature": 44.61
    },
    {
        "beetbox_id": "beetbox005",
        "coordinates": "POINT(44.289452 -117.215825)",
        "piler_id": "1",
        "temperature_time": "2024-10-08T05:19:54.000000",
        "temperature": 42.69
    },
    {
        "beetbox_id": "beetbox004",
        "coordinates": "POINT(44.288418 -117.216843)",
        "piler_id": "3",
        "temperature_time": "2024-10-12T10:35:28.000000",
        "temperature": 37.53
    },
    {
        "beetbox_id": "beetbox006",
        "coordinates": "POINT(44.290529 -117.217198)",
        "piler_id": "2",
        "temperature_time": "2024-10-13T16:47:32.000000",
        "temperature": 38.53
    },
    {
        "beetbox_id": "beetbox001",
        "coordinates": "POINT(44.283275 -117.219654)",
        "piler_id": "1",
        "temperature_time": "2024-10-08T01:08:17.000000",
        "temperature": 36.57
    },
    {
        "beetbox_id": "beetbox014",
        "coordinates": "POINT(44.29156 -117.219318)",
        "piler_id": "1",
        "temperature_time": "2024-10-09T04:24:46.000000",
        "temperature": 45.54
    },
    {
        "beetbox_id": "beetbox009",
        "coordinates": "POINT(44.287554 -117.217675)",
        "piler_id": "3",
        "temperature_time": "2024-10-13T08:14:09.000000",
        "temperature": 38.7
    },
    {
        "beetbox_id": "beetbox008",
        "coordinates": "POINT(44.296515 -117.226372)",
        "piler_id": "3",
        "temperature_time": "2024-10-11T22:29:48.000000",
        "temperature": 43.88
    },
    {
        "beetbox_id": "beetbox013",
        "coordinates": "POINT(44.283034 -117.226578)",
        "piler_id": "3",
        "temperature_time": "2024-10-11T01:35:45.000000",
        "temperature": 43.22
    },
    {
        "beetbox_id": "beetbox009",
        "coordinates": "POINT(44.290949 -117.22391)",
        "piler_id": "2",
        "temperature_time": "2024-10-13T18:41:26.000000",
        "temperature": 35.88
    },
    {
        "beetbox_id": "beetbox020",
        "coordinates": "POINT(44.295676 -117.228184)",
        "piler_id": "3",
        "temperature_time": "2024-10-14T14:44:27.000000",
        "temperature": 42.12
    },
    {
        "beetbox_id": "beetbox001",
        "coordinates": "POINT(44.284586 -117.226572)",
        "piler_id": "1",
        "temperature_time": "2024-10-12T03:38:46.000000",
        "temperature": 41.45
    },
    {
        "beetbox_id": "beetbox011",
        "coordinates": "POINT(44.297022 -117.232159)",
        "piler_id": "2",
        "temperature_time": "2024-10-08T21:12:30.000000",
        "temperature": 42.83
    },
    {
        "beetbox_id": "beetbox020",
        "coordinates": "POINT(44.282555 -117.227434)",
        "piler_id": "2",
        "temperature_time": "2024-10-13T01:04:53.000000",
        "temperature": 39.58
    },
    {
        "beetbox_id": "beetbox012",
        "coordinates": "POINT(44.292553 -117.230853)",
        "piler_id": "2",
        "temperature_time": "2024-10-09T12:32:47.000000",
        "temperature": 36.78
    },
    {
        "beetbox_id": "beetbox016",
        "coordinates": "POINT(44.289979 -117.230674)",
        "piler_id": "1",
        "temperature_time": "2024-10-13T05:01:13.000000",
        "temperature": 41.85
    },
    {
        "beetbox_id": "beetbox011",
        "coordinates": "POINT(44.287146 -117.225809)",
        "piler_id": "1",
        "temperature_time": "2024-10-11T12:03:02.000000",
        "temperature": 36.36
    },
    {
        "beetbox_id": "beetbox004",
        "coordinates": "POINT(44.289058 -117.226105)",
        "piler_id": "3",
        "temperature_time": "2024-10-12T00:46:48.000000",
        "temperature": 37.48
    },
    {
        "beetbox_id": "beetbox015",
        "coordinates": "POINT(44.291954 -117.232261)",
        "piler_id": "2",
        "temperature_time": "2024-10-14T18:05:47.000000",
        "temperature": 35.41
    },
    {
        "beetbox_id": "beetbox017",
        "coordinates": "POINT(44.283589 -117.230112)",
        "piler_id": "1",
        "temperature_time": "2024-10-08T22:58:51.000000",
        "temperature": 37.22
    },
    {
        "beetbox_id": "beetbox013",
        "coordinates": "POINT(44.297406 -117.216275)",
        "piler_id": "3",
        "temperature_time": "2024-10-08T15:10:47.000000",
        "temperature": 41.62
    },
    {
        "beetbox_id": "beetbox019",
        "coordinates": "POINT(44.291749 -117.219735)",
        "piler_id": "1",
        "temperature_time": "2024-10-08T12:33:23.000000",
        "temperature": 38.71
    },
    {
        "beetbox_id": "beetbox019",
        "coordinates": "POINT(44.286728 -117.220176)",
        "piler_id": "2",
        "temperature_time": "2024-10-12T04:44:18.000000",
        "temperature": 41.46
    },
    {
        "beetbox_id": "beetbox013",
        "coordinates": "POINT(44.283194 -117.226231)",
        "piler_id": "3",
        "temperature_time": "2024-10-14T07:57:34.000000",
        "temperature": 44.92
    },
    {
        "beetbox_id": "beetbox014",
        "coordinates": "POINT(44.284755 -117.225629)",
        "piler_id": "1",
        "temperature_time": "2024-10-08T03:41:57.000000",
        "temperature": 40.88
    },
    {
        "beetbox_id": "beetbox001",
        "coordinates": "POINT(44.287598 -117.225688)",
        "piler_id": "3",
        "temperature_time": "2024-10-14T00:29:40.000000",
        "temperature": 41.92
    }
]
